{"id":"02361","name":"Абакшин Евгений Николаевич ","link":"pages/02361.html","club":"Мегаполис (г.СПб)","class_classic":"B","class_dnd":"M","A":"0","B":"0","C":"12","D":"12","E":"0","Ch":"0","S":"0","M":"0","RS":"0","Beg":"0","story_classic":"10.05.2015 — Чемпионат Москвы 2015г.Москва : B13/17<br><br>18.04.2015 — Чемпионат Санкт-Петербурга 2015 : (В-А2)B1/2<br><br>06.12.2014 — Чемпионат России 2014г.Москва : (Е-А40-41)B29/30<br><br>29.06.2014 — Кубок Лета г.СПб : C1/3<br><br>14.12.2013 — Чемпионат России 2013г.Москва : (ДнД СВ5)C2/42+3<br><br>24.11.2013 — Кубок морской славы г.СПб : (С-В5)C2/2<br><br>12.10.2013 — Dance weekend г.СПб : C8/18+1<br><br>18.05.2013 — Чемпионат Москвы2013 : C23/49+1<br><br>21.04.2013 — For Friends Only 2013 г.СПб : C5/9<br><br>23.03.2013 — Nord Cup г.Санкт-Петербург : C28/31<br><br>09.12.2012 — Космос 2012 г.СПб : (С-В6-7)C4/7<br><br>25.11.2012 — Кубок Морской Славыг.СПб : (Д-В6)C3/8+1<br><br>03.11.2012 — Чемпионат России 2012 г.Москва : (Д-А30-32)C1/19+5<br><br>14.04.2012 — КубокСевернойСтолицы : C19/24<br><br>10.12.2011 — ЧемпионатРоссии2011 : (Д-А67-83)C44/44<br><br>03.12.2011 — Космос2011 : (С-Б6)C4/9+1<br><br>25.06.2011 — Кубок Лета 2011(г.СПб) : D9/27+1<br><br>04.06.2011 — Кубок В.Новгорода2011 : D5/17+2<br><br>14.05.2011 — ЧемпионатМосквы2011 : D10/52+2<br><br>09.04.2011 — Кубок СевернойСтолицы : D17/42+1<br><br>27.02.2011 — Зимний Кубок СПб : D20/31<br><br>19.12.2010 — Кубок Лета, 4 тур (СПб) : D20/20<br><br>05.09.2010 — Кубок Лета 2010 (2й тур) : D6/19+2<br><br>22.05.2010 — Куб.ВеликогоНовгорода : D4/18+3<br><br>25.04.2010 — Кубок Салюта : D22/40<br><br>17.04.2010 — Кубок Сев.Стол. : D12/33+1<br><br>28.03.2010 — Простые движ.(СПб) : D29/30<br><br>","story_dnd":"11.05.2015 — Чемпионат Москвы 2015г.Москва :  M18/19<br><br>18.04.2015 — Чемпионат Санкт-Петербурга 2015 : (M-S5) M3/4<br><br>07.12.2014 — Чемпионат России 2014г.Москва :  M14/23<br><br>"}