{"id":"02526","name":"Злобин Роман Александрович ","link":"pages/02526.html","club":"Движение","class_classic":"C","class_dnd":"RS","A":"0","B":"0","C":"4","D":"14","E":"0","Ch":"0","S":"0","M":"0","RS":"0","Beg":"0","story_classic":"29.04.2012 — Кубок Ренессанса г.Барнаул : (Е-В8-9)B9/9<br><br>09.03.2012 — Кубок КХК Движение Красноярск : C6/18+2<br><br>10.12.2011 — ЧемпионатРоссии2011 : (Д-А38-47)C12/41+1<br><br>26.11.2011 — Буревестник2011 : (Е-А12-14)C5/13+1<br><br>10.09.2011 — Открытие Сезона : D1/27+5<br><br>21.08.2011 — Динамиада : D1/14+4<br><br>07.08.2011 — Летний КубокVestadance : D3/10+2<br><br>12.06.2011 — Держи Ритм16 : D3/4<br><br>28.05.2011 — Командное первенство 2011 : D19/35<br><br>22.05.2011 — Весенний КубокVestaDance : D14/26<br><br>24.04.2011 — Держи Ритм 15 : D14/31+1<br><br>02.04.2011 — Динамиада : D12/28+1<br><br>13.03.2011 — Новая волна : D9/13<br><br>07.03.2011 — Весенний КубокСокольников : D11/11<br><br>26.02.2011 — Зимний кубок Vestadance : D7/13<br><br>13.02.2011 — Держи Ритм 14 : D17/24<br><br>06.02.2011 — Кубок Чемпионов 2 : D17/42+1<br><br>23.01.2011 — Дебют-2011 : D22/28<br><br>02.05.2010 — Куб.Ренессанса : D21/27<br><br>","story_dnd":""}