{"id":"03302","name":"Засухин Сергей Александрович ","link":"pages/03302.html","club":"Движение (г.Красноярск)","class_classic":"E","class_dnd":"BG","A":"0","B":"0","C":"0","D":"0","E":"1","Ch":"0","S":"0","M":"0","RS":"0","Beg":"0","story_classic":"02.06.2012 — На пути к звездам Красноярск : D9/12<br><br>22.04.2012 — Открытый турнирг.Красноярск : E11/16<br><br>16.10.2011 — Открытый турнир Красноярск : D18/26<br><br>28.05.2011 — На пути к звёздам : D20/23<br><br>24.04.2011 — Открытый турнир E+D класс : D20/24<br><br>12.03.2011 — Кубок Движенияг.Красноярск : D28/31<br><br>06.02.2011 — Открытый турнирг.Красноярск : E7/14+1<br><br>","story_dnd":""}