{"id":"03977","name":"Ивбуль Алексей Александрович ","link":"pages/03977.html","club":"Strikly (г.СПб)","class_classic":"D","class_dnd":"BG","A":"0","B":"0","C":"0","D":"0","E":"5","Ch":"0","S":"0","M":"0","RS":"0","Beg":"0","story_classic":"02.05.2014 — Чемпионат Санкт-Петербурга : E3/19+3<br><br>14.03.2014 — Nord Cup г.СПб : E32/50<br><br>12.10.2013 — Dance weekend г.СПб : E18/20<br><br>21.01.2012 — ПозитивныйКубок(СПб) : E5/17+2<br><br>03.12.2011 — Космос2011 : E13/17<br><br>30.10.2011 — КубокМорскойСлавы : E16/28<br><br>","story_dnd":""}