{"id":"04945","name":"Шепчук Евгений Владимирович ","link":"pages/04945.html","club":"Альтернатива (г.Барнаул)","class_classic":"D","class_dnd":"BG","A":"0","B":"0","C":"0","D":"0","E":"5","Ch":"0","S":"0","M":"0","RS":"0","Beg":"0","story_classic":"13.12.2014 — Открытый Кубок г.Новосибирск : D18/19<br><br>15.11.2014 — Осенний кубок Ренессанса г.Барнаул : D12/14<br><br>11.10.2014 — Перезагрузка г.Новосибирск : D14/16<br><br>03.05.2014 — Кубок Ренессанса 2014 г.Барнаул : D19/19<br><br>30.11.2013 — Открытый Кубок г.Новосибирска : (ДнД Е-Д48-49)D48/48<br><br>09.11.2013 — Осенний кубок Ренессанса г.Барнаул : (ДнД Е-Д7)D7/8<br><br>16.03.2013 — Открытый Кубок Движения г.Красноярск : D15/19<br><br>23.02.2013 — Февральский марафон г.Новосибирск : E8/26+2<br><br>15.12.2012 — Звезды Сибири г.Новосибирск : E4/22+3<br><br>20.10.2012 — Осенний Кубок Ренессанса г.Барнаул : E18/18<br><br>","story_dnd":"03.05.2015 — Чемпионат Урала г.Екатеринбург :  BG17/24<br><br>13.12.2014 — Открытый Кубок г.Новосибирск :  BG20/35<br><br>15.11.2014 — Осенний кубок Ренессанса г.Барнаул :  BG19/23<br><br>11.10.2014 — Перезагрузка г.Новосибирск :  BG15/26<br><br>"}