{"id":"04990","name":"Нагаев Антон Сергеевич ","link":"pages/04990.html","club":"Чердак (г.Красноярск)","class_classic":"D","class_dnd":"BG","A":"0","B":"0","C":"1","D":"3","E":"5","Ch":"0","S":"0","M":"0","RS":"0","Beg":"2","story_classic":"21.06.2015 — Хастл над Енисеем г.Красноярск : D4/9+1<br><br>06.06.2015 — На пути к звездам г.Красноярск  : D4/13+2<br><br>14.03.2015 — Открытый кубок Движенияг.Красноярск : D9/16<br><br>15.02.2015 — Открытый турнир E-D классов г.Красноярск : D7/8<br><br>08.06.2014 — На пути к звездам г.Красноярск : (Е-С4)C4/8+1<br><br>09.03.2014 — Шаг Вперед г.Красноярск : (ДнД Е-Д4)D4/6<br><br>16.02.2013 — Шаг вперед г.Красноярск : E3/14+3<br><br>21.10.2012 — Открытый турнир ED г.Красноярск : E6/19+2<br><br>","story_dnd":"06.06.2015 — На пути к звездам г.Красноярск  :  BG4/21+2<br><br>"}