{"id":"05610","name":"Бевз Ольга Васильевна ","link":"pages/05610.html","club":"Smile","class_classic":"D","class_dnd":"BG","A":"0","B":"0","C":"0","D":"4","E":"6","Ch":"0","S":"0","M":"0","RS":"0","Beg":"7","story_classic":"17.05.2014 — Чемпионат Москвы2014 : (ДнД Е-Д2)D2/68+4<br><br>14.12.2013 — Чемпионат России 2013г.Москва : D37/66<br><br>18.05.2013 — Чемпионат Москвы2013 : E1/60+6<br><br>","story_dnd":"11.05.2015 — Чемпионат Москвы 2015г.Москва :  BG24/118+1<br><br>07.12.2014 — Чемпионат России 2014г.Москва :  BG3/118+6<br><br>25.10.2014 — Красный октябрь г.Москва :  BG21/50<br><br>"}