{"id":"05682","name":"Громов Александр Сергеевич ","link":"pages/05682.html","club":"MMDance (г.СПб),Мегаполис (г.СПб)","class_classic":"D","class_dnd":"BG","A":"0","B":"0","C":"0","D":"0","E":"6","Ch":"0","S":"0","M":"0","RS":"0","Beg":"0","story_classic":"23.08.2014 — Просто конкурс г.СПб : (ДнД Е-Д6)D6/13<br><br>02.05.2014 — Чемпионат Санкт-Петербурга : E4/19+3<br><br>14.03.2014 — Nord Cup г.СПб : E17/50+1<br><br>12.10.2013 — Dance weekend г.СПб : E10/20+1<br><br>16.06.2013 — Кубок Лета г.СПб : E8/21+1<br><br>","story_dnd":""}