{"id":"06320","name":"Степанов Дмитрий Владимирович ","link":"pages/06320.html","club":"Мегаполис (г.СПб)","class_classic":"E","class_dnd":"BG","A":"0","B":"0","C":"0","D":"0","E":"1","Ch":"0","S":"0","M":"0","RS":"0","Beg":"0","story_classic":"14.12.2014 — Танцевальная зима г.СПб : E13/26+1<br><br>9.11.2014 — Кубок Морской Славы г.СПб : E26/26<br><br>14.03.2014 — Nord Cup г.СПб : E42/50<br><br>","story_dnd":"14.12.2014 — Танцевальная зима г.СПб :  BG28/28<br><br>9.11.2014 — Кубок Морской Славы г.СПб :  BG32/32<br><br>"}