{"id":"07241","name":"Мустафин Алексей Владиславович ","link":"pages/07241.html","club":"Движение (г.Красноярск),Чердак (г.Красноярск)","class_classic":"E","class_dnd":"BG","A":"0","B":"0","C":"0","D":"0","E":"2","Ch":"0","S":"0","M":"0","RS":"0","Beg":"1","story_classic":"11.07.2015 — Летний Кубок Движенияг.Новосибирск : E7/8<br><br>21.06.2015 — Хастл над Енисеем г.Красноярск : E3/8+1<br><br>06.06.2015 — На пути к звездам г.Красноярск  : E6/16+1<br><br>26.04.2015 — Открытый турнир E+D классовг.Красноярск : E7/13<br><br>14.03.2015 — Открытый кубок Движенияг.Красноярск : E11/11<br><br>15.02.2015 — Открытый турнир E-D классов г.Красноярск : E12/12<br><br>","story_dnd":"11.07.2015 — Летний Кубок Движенияг.Новосибирск :  BG12/16<br><br>21.06.2015 — Хастл над Енисеем г.Красноярск :  BG3/9+1<br><br>06.06.2015 — На пути к звездам г.Красноярск  :  BG12/21<br><br>26.04.2015 — Открытый турнир E+D классовг.Красноярск :  BGG10/15<br><br>"}